  {
    "name": "Squirt Gun",
    "automation": [
      {
        "type": "target",
        "target": "each",
        "effects": [
          {
            "type": "attack",
            "hit": [
              {
                "type": "damage",
                "damage": "(1d100+{dexterityMod})*0 [water]",
                "overheal": false
              },
              {
                "type": "ieffect2",
                "name": "Damp",
                "duration": 2,
                "desc": "You're now damp"
              }
            ],
            "miss": [],
            "attackBonus": "proficiencyBonus+dexterityMod"
          }
        ]
      },
      {
        "type": "text",
        "text": "Works best if you say pew pew while firing, requires pumping between shots"
      }
    ],
    "_v": 2
  }